setup.py
simpletextwriter.egg-info/PKG-INFO
simpletextwriter.egg-info/SOURCES.txt
simpletextwriter.egg-info/dependency_links.txt
simpletextwriter.egg-info/top_level.txt
write/__init__.py