Metadata-Version: 2.4
Name: simpletextwriter
Version: 0.2
Summary: A simple typewriter-style text output function
Author: Hackitech
Requires-Python: >=3.6
Dynamic: author
Dynamic: requires-python
Dynamic: summary
